[
  {
    "title": "VisitUs",
    "imageSrc": "projects/Visitus.png",
    "description":"Travel package booking site",
    "skills": [],
    "demo": "",
    "source": ""
  },
  {
    "title": "Homyz",
    "imageSrc": "projects/Homyz.png",
    "description": "This project is a real estate Website",
    "skills": [],
    "demo": "https://real-estate-myapp.netlify.app/",
    "source": "https://github.com/bhawnachandla/my-real-estate-app.git"
  },
  {
    "title": "Landing Page",
    "imageSrc": "projects/starbucks.png",
    "description": "Responsive and attractive landing of Starbucks  ",
    "skills": [],
    "demo": "https://bhawnachandla.github.io/starbuck-landing-page/",
    "source": "https://github.com/bhawnachandla/starbuck-landing-page.git"
  }, 
  {
    "title": "Tic Tac Toe",
    "imageSrc": "projects/tictac.png",
    "description": "Play online with this interactive JavaScript game!",
    "skills": [],
    "demo": "https://bhawnachandla.github.io/Tic-Tac-Toe/",
    "source": "https://github.com/bhawnachandla/Tic-Tac-Toe.git"
  },
  {
    "title": "My Portfolio",
    "imageSrc": "projects/portfolio.png",
    "description": "Explore my portfolio, crafted with React for engaging experience.",
    "skills": [],
    "demo": "https://bhawna-port-folio.netlify.app/",
   "source": "https://github.com/bhawnachandla/portfolio.git"
  },
  {
    "title": "Weather App",
    "imageSrc": "projects/weatherapp.png",
    "description": "This weather app is created using HTML,CSS and JS.",
    "skills": [],
    "demo": "https://bhawnachandla.github.io/weather-app/",
   "source": "https://github.com/bhawnachandla/weather-app.git"
  },
  {
    "title": "Keeper App",
    "imageSrc": "projects/keeperapp.png",
    "description": "This is a note taking app created in react.",
    "skills": [],
    "demo": "https://mynote-keeping-app.netlify.app/",
   "source": "https://github.com/bhawnachandla/Keeper-App.git"
  },
  {
    "title": "To Do App",
    "imageSrc": "projects/todoapp.png",
    "description": "A simple to do app created in react.",
    "skills": [],
    "demo": "https://myapp-to-do.netlify.app/",
   "source": "https://github.com/bhawnachandla/To-Do-App.git"
  }
]
